README.md
setup.py
colorix/__init__.py
colorix/colormodes.py
colorix/utils.py
colorix.egg-info/PKG-INFO
colorix.egg-info/SOURCES.txt
colorix.egg-info/dependency_links.txt
colorix.egg-info/top_level.txt