Metadata-Version: 2.1
Name: colorix
Version: 0.1.5
Summary: A Python3 module for colors
Home-page: https://github.com/angelCarias/colorix
Author: Tekgar
License: UNKNOWN
Download-URL: https://github.com/angelCarias/colorix/archive/v0.1.5.tar.gz
Platform: UNKNOWN
Requires-Python: >=3.6
